jewel/__init__.py
jewel/__main__.py
jewel/formats/__init__.py
jewel-0.1.0.dist-info/entry_points.txt
jewel-0.1.0.dist-info/LICENSE
jewel-0.1.0.dist-info/WHEEL
jewel-0.1.0.dist-info/METADATA
jewel-0.1.0.dist-info/RECORD
