Metadata-Version: 2.1
Name: jewel
Version: 0.1.0
Summary: Rich Python code snippets.
License: Apache-2.0
Author: Aaron Stephens
Author-email: aaronjst93@gmail.com
Requires-Python: >=3.6.3,<4.0.0
Classifier: License :: OSI Approved :: Apache Software License
Classifier: Programming Language :: Python :: 3
Classifier: Programming Language :: Python :: 3.10
Classifier: Programming Language :: Python :: 3.7
Classifier: Programming Language :: Python :: 3.8
Classifier: Programming Language :: Python :: 3.9
Requires-Dist: rich (>=12.1.0,<13.0.0)
